amz_parser/__init__.py
amz_parser/listing_parser.py
amz_parser/review_parser.py
amz_parser-0.9.6.dist-info/METADATA
amz_parser-0.9.6.dist-info/WHEEL
amz_parser-0.9.6.dist-info/top_level.txt
amz_parser-0.9.6.dist-info/RECORD
